.gitignore
CHANGES.txt
COPYING
COPYING.LESSER
README.txt
setup.py
examples/bibitex/bibitex.py
examples/bibitex/form.pt
examples/bibitex/forms.py
examples/bibitex/index.pt
examples/bibitex/models.py
examples/pyramid-attachs/.gitignore
examples/pyramid-attachs/CHANGES.txt
examples/pyramid-attachs/MANIFEST.in
examples/pyramid-attachs/README.txt
examples/pyramid-attachs/development.ini
examples/pyramid-attachs/production.ini
examples/pyramid-attachs/setup.cfg
examples/pyramid-attachs/setup.py
examples/pyramid-attachs/build/lib.linux-x86_64-2.6/pyramidattachs/__init__.py
examples/pyramid-attachs/build/lib.linux-x86_64-2.6/pyramidattachs/resources.py
examples/pyramid-attachs/build/lib.linux-x86_64-2.6/pyramidattachs/tests.py
examples/pyramid-attachs/build/lib.linux-x86_64-2.6/pyramidattachs/views.py
examples/pyramid-attachs/build/lib.linux-x86_64-2.6/pyramidattachs/static/favicon.ico
examples/pyramid-attachs/build/lib.linux-x86_64-2.6/pyramidattachs/static/footerbg.png
examples/pyramid-attachs/build/lib.linux-x86_64-2.6/pyramidattachs/static/headerbg.png
examples/pyramid-attachs/build/lib.linux-x86_64-2.6/pyramidattachs/static/ie6.css
examples/pyramid-attachs/build/lib.linux-x86_64-2.6/pyramidattachs/static/middlebg.png
examples/pyramid-attachs/build/lib.linux-x86_64-2.6/pyramidattachs/static/pylons.css
examples/pyramid-attachs/build/lib.linux-x86_64-2.6/pyramidattachs/static/pyramid-small.png
examples/pyramid-attachs/build/lib.linux-x86_64-2.6/pyramidattachs/static/pyramid.png
examples/pyramid-attachs/build/lib.linux-x86_64-2.6/pyramidattachs/static/transparent.gif
examples/pyramid-attachs/build/lib.linux-x86_64-2.6/pyramidattachs/templates/mytemplate.pt
examples/pyramid-attachs/pyattachs/.couchappignore
examples/pyramid-attachs/pyattachs/.couchapprc
examples/pyramid-attachs/pyattachs/README.md
examples/pyramid-attachs/pyattachs/_id
examples/pyramid-attachs/pyattachs/couchapp.json
examples/pyramid-attachs/pyattachs/language
isisdm.egg-info/PKG-INFO
isisdm.egg-info/SOURCES.txt
isisdm.egg-info/dependency_links.txt
isisdm.egg-info/namespace_packages.txt
isisdm.egg-info/not-zip-safe
isisdm.egg-info/requires.txt
isisdm.egg-info/top_level.txt
