Metadata-Version: 1.0
Name: isisdm
Version: 0.2.3
Summary: ISIS-DM allows programmers to express constraints and functionality similar to those of the CDS/ISIS Field Definition Table and the CDS/ISIS Formatting Language, but in contemporary, object-oriented programming languages.
Home-page: http://reddes.bvsalud.org/
Author: BIREME/OPAS/OMS
Author-email: isisnbp-devel@listas.bireme.br
License: LGPL v2.1 (http://www.gnu.org/licenses/lgpl-2.1.txt)
Download-URL: https://github.com/bireme/isisdm
Keywords: isis application database bireme
Platform: UNKNOWN
Classifier: Development Status :: 3 - Alpha
Classifier: Intended Audience :: Developers
Classifier: Programming Language :: Python
Classifier: Topic :: Internet :: WWW/HTTP
Classifier: Topic :: Internet :: WWW/HTTP :: WSGI
Classifier: Topic :: Internet :: WWW/HTTP :: WSGI :: Middleware
